antidupe/__init__.py
antidupe/main.py
antidupe/utilities.py
antidupe-0.0.8.dist-info/LICENSE
antidupe-0.0.8.dist-info/METADATA
antidupe-0.0.8.dist-info/WHEEL
antidupe-0.0.8.dist-info/top_level.txt
antidupe-0.0.8.dist-info/RECORD
