Metadata-Version: 2.1
Name: antidupe
Version: 0.0.8
Summary: Image deduplicator using CNN, Cosine Similarity, Image Hashing, Structural Similarity Index Measurement, and Euclidean Distance
Home-page: https://github.com/manbehindthemadness/antidupe
Author: Manbehindthemadness
Author-email: manbehindthemadness@gmail.com
Classifier: Programming Language :: Python :: 3
Classifier: License :: OSI Approved :: Apache Software License
Classifier: Operating System :: OS Independent
Requires-Python: >=3.8
License-File: LICENSE
Requires-Dist: SSIM-PIL
Requires-Dist: imagededup
Requires-Dist: matplotlib
Requires-Dist: imagehash
Requires-Dist: efficientnet-pytorch
Requires-Dist: numpy
Requires-Dist: Pillow
Requires-Dist: torch >=2.0.0
Requires-Dist: torchvision >=0.17.0
